mzprojection/__init__.py
mzprojection/mzprojection.py
mzprojection_pkg-0.0.3.dist-info/LICENSE
mzprojection_pkg-0.0.3.dist-info/METADATA
mzprojection_pkg-0.0.3.dist-info/WHEEL
mzprojection_pkg-0.0.3.dist-info/top_level.txt
mzprojection_pkg-0.0.3.dist-info/RECORD
