Metadata-Version: 2.1
Name: mzprojection-pkg
Version: 0.0.3
Summary: mzprojection package
Home-page: https://github.com/smaeyama/mzprojection
Author: Shinya Maeyama
Author-email: smaeyama@p.phys.nagoya-u.ac.jp
License: UNKNOWN
Project-URL: Bug Tracker, https://github.com/smaeyama/mzprojection/issues
Platform: UNKNOWN
Classifier: Programming Language :: Python :: 3
Classifier: License :: OSI Approved :: MIT License
Classifier: Operating System :: OS Independent
Requires-Python: >=3.6
License-File: LICENSE
